[
  {
    "ParameterKey": "PipelineName",
    "ParameterValue": "qapipeline"
  },
  {
    "ParameterKey": "ApplicationName",
    "ParameterValue": "digiroad2"
  },
  {
    "ParameterKey": "EcsClusterName",
    "ParameterValue": "qa-digiroad2-ECS-Cluster-Private"
  },
  {
    "ParameterKey": "EcsServiceName",
    "ParameterValue": "qa-digiroad2-ECS-Service-Private"
  },
  {
    "ParameterKey": "EcrRepositoryName",
    "ParameterValue": "digiroad2test"
  },
  {
    "ParameterKey": "CodeBuildName",
    "ParameterValue": "digiroad2_test_build"
  },
  {
    "ParameterKey": "GitBranchName",
    "ParameterValue": "NextRelease"
  },
  {
    "ParameterKey": "GitHubWebhookSecret",
    "ParameterValue": "arn:aws:secretsmanager:eu-west-1:475079312496:secret:GITHUB_PAT-CqR1N2"
  },
  {
    "ParameterKey": "GitRepositoryName",
    "ParameterValue": "digiroad2"
  },
  {
    "ParameterKey": "GitHubOwner",
    "ParameterValue": "finnishtransportagency"
  },
  {
    "ParameterKey": "VpcIDOfSystem",
    "ParameterValue": "vpc-0f430b7fedef04ba3"
  }
]